{
  "day": 50,
  "stage": {
    "name": "练习篇",
    "stageNumber": 3,
    "color": "#7BBE7E",
    "bgColor": "#D8EDD9"
  },
  "theme": "别再钻牛角尖",
  "coreLine": "反刍只会越想越糟",
  "totalPages": 25,
  "pages": [
    {
      "id": "p1",
      "next": "p2",
      "buttonText": "开始今天",
      "type": "content",
      "body": "欢迎进入练习篇第 16 天，也是 71 天里过半的那一天。\n\n先做一个 30 秒的小测试。\n\n回想一件最近让你不爽的事。可以是一次跟人吵架，可以是一条不该发的消息，可以是工作里一个失误。\n\n现在回答：\n\n- 过去 7 天，你在脑子里「重播」过它几次？\n- 每次重播你得出过新结论吗？\n- 重播完心情是变好还是变差？\n\n绝大多数人答案是：**重播 5 到 20 次，没新结论，心情更差**。\n\n这就是今天的主角：**反刍**（rumination）。\n\n把同一件事在脑子里来回播。每播一遍以为自己在「思考」，实际上只是在重复**「为什么是我 / 为什么会这样 / 我怎么这么蠢」**。\n\n研究反刍最深的一个人姓 Nolen-Hoeksema，耶鲁心理系教授，做了 30 年研究，直到 2013 年去世。她最核心的一句结论是：\n\n**反刍是抑郁性别差异背后的核心机制。** 女性抑郁率是男性的 2 倍，反刍倾向是关键中介变量。\n\n今天把反刍讲清楚，给你 3 个亲测可用的打断方法。\n\n从今天开始进入练习篇第三模块：**情绪调节**。"
    },
    {
      "id": "p2",
      "next": "p3",
      "type": "single_choice",
      "category": "awareness",
      "question": "你最近 7 天有没有过「一件不爽的事在脑子里反复回放停不下来」的状态？",
      "options": [
        {
          "id": "opt1",
          "label": "几乎每天都有，停不下来",
          "feedback": "典型反刍模式，今天的练习直接针对你。"
        },
        {
          "id": "opt2",
          "label": "有 2 到 3 次，单次能持续半小时以上",
          "feedback": "常见水平。今天教你怎么把单次时长砍到 5 分钟内。"
        },
        {
          "id": "opt3",
          "label": "偶尔，但很快能切走",
          "feedback": "调节能力相对健康，今天再加固方法论。"
        },
        {
          "id": "opt4",
          "label": "几乎没有，我不太纠结过去的事",
          "feedback": "难得。也可能是你回避了情绪，今天的觉察题帮你区分。"
        },
        {
          "id": "opt5",
          "label": "我说不清楚算不算",
          "feedback": "能如实说出『说不清』就是觉察的开始。今天会让你看清反刍的具体长相。"
        }
      ]
    },
    {
      "id": "p3",
      "next": "p4",
      "type": "text",
      "category": "awareness",
      "question": "凭直觉写下来：\n\n**「过去 7 天里我最爱反刍的那件事 / 那个画面是 ____。」**\n\n不必写细节。写一个关键词或一句话就行。",
      "placeholder": "例如：「上周三那次跟妈妈的电话」「3 个月前那条发错的消息」「同事开会时那个眼神」「去年那场没谈成的合作」「想不起来具体哪件，就是脑子里总有声音在转」……",
      "required": true
    },
    {
      "id": "p4",
      "title": "📖 今日完整阅读",
      "next": "p5",
      "buttonText": "读完了，开始做题",
      "type": "content"
    },
    {
      "id": "p5",
      "next": "p6",
      "type": "single_choice",
      "category": "knowledge",
      "question": "下面哪一种最符合反刍的定义？",
      "options": [
        {
          "id": "opt1",
          "label": "思考一件事的因果、得出新结论",
          "feedback": ""
        },
        {
          "id": "opt2",
          "label": "重复地、被动地回放同一件负面事件 / 同一组负面感受，且没有产生新结论 / 新行动",
          "feedback": ""
        },
        {
          "id": "opt3",
          "label": "写日记复盘",
          "feedback": ""
        },
        {
          "id": "opt4",
          "label": "跟朋友聊一件烦心事",
          "feedback": ""
        }
      ],
      "mustCorrect": true,
      "correctAnswer": "opt2"
    },
    {
      "id": "p6",
      "next": "p7",
      "type": "multiple_choice",
      "category": "knowledge",
      "question": "下面哪些属于 **反思**，不属于反刍？（多选）",
      "options": [
        {
          "id": "opt1",
          "label": "「上次开会我没准备好。下次提前 30 分钟过一遍 PPT 就行。」",
          "feedback": ""
        },
        {
          "id": "opt2",
          "label": "「为什么我总是这样？我是不是天生就笨？」",
          "feedback": ""
        },
        {
          "id": "opt3",
          "label": "「这次冲突里我哪一句话踩了她的雷？下次换一个说法。」",
          "feedback": ""
        },
        {
          "id": "opt4",
          "label": "「她当时那个眼神是什么意思？是不是讨厌我？」",
          "feedback": ""
        }
      ],
      "mustCorrect": true,
      "correctAnswers": [
        "opt1, opt3"
      ]
    },
    {
      "id": "p7",
      "next": "p8",
      "type": "true_false",
      "category": "knowledge",
      "statement": "「Nolen-Hoeksema 30 年研究证明：反刍预测未来抑郁发作，抑郁也加重反刍，两者形成双向放大循环。这条机制还能解释为什么女性抑郁率约是男性的 2 倍：女性反刍倾向显著更高，是性别差异背后的核心中介变量。」这段话对吗？",
      "mustCorrect": true,
      "correctAnswer": true
    },
    {
      "id": "p8",
      "next": "p9",
      "type": "single_choice",
      "category": "knowledge",
      "question": "下面哪一种**最不是**反刍打断的有效方法？",
      "options": [
        {
          "id": "opt1",
          "label": "分心：找一件需要专注的事做（运动、做菜、跟朋友说话）",
          "feedback": ""
        },
        {
          "id": "opt2",
          "label": "问题解决：把模糊焦虑拆成「下一步具体动作」",
          "feedback": ""
        },
        {
          "id": "opt3",
          "label": "行为激活：先动起来再说，不等心情好",
          "feedback": ""
        },
        {
          "id": "opt4",
          "label": "在心里反复告诉自己「想清楚为止不许停」",
          "feedback": ""
        }
      ],
      "mustCorrect": true,
      "correctAnswer": "opt4"
    },
    {
      "id": "p9",
      "title": "💡 它和你有什么关系",
      "next": "p10",
      "buttonText": "明白了",
      "type": "content",
      "body": "你为什么停不下来？这里面有 3 个生理 + 心理机制。\n\n**机制 1：默认模式网络过度激活**\n\n你的大脑有一组在你「什么都没干」时自动启动的脑区，叫默认模式网络（DMN）。它的本职是自我回顾 / 模拟社交场景。反刍状态下默认模式网络持续过度激活，前额叶皮层（理性调节）下调失败，结果你「看着不动，脑子高速空转」。\n\n**机制 2：负强化陷阱**\n\n反刍的当下你会有一种「我在认真处理它」的错觉。这种错觉短期降低焦虑，所以大脑学会了**「下次焦虑还来这一招」**。它给你回报，所以你停不下来。\n\n**机制 3：抽象思维放大效应**\n\n英国心理学家 Watkins 2008 年的研究指出：反刍偏好**抽象提问**（「为什么我总这样」「我是不是天生有缺陷」），抽象提问没法解决也没法证伪，所以越想越深。\n\n3 个机制合起来 → 你的脑子被劫持了 → 你以为在思考，实际在转圈。\n\n破局思路只有 3 条，都被研究反复验证。\n\n**A. 分心（短期断链）**\n找一件**需要专注 + 占用工作记忆**的事做 15 到 30 分钟。运动 / 做菜 / 打电话 / 玩一个需要动脑的游戏。被动消遣（刷短视频）效果差。它不占工作记忆，反刍会在后台继续。\n\n**B. 问题解决（把抽象拉成具体）**\n把「为什么是我」改写成「**在 X 时刻 Y 事件我做了 Z，下次我可以做 W**」。Watkins 把这个叫具体思维，专门拆抽象反刍的解药。\n\n**C. 行为激活（不等心情好）**\n反刍最爱在「什么都没干」时启动。先动起来（出门走 10 分钟 / 收拾桌面 / 给一个人发消息），动作本身会启动前额叶，把默认模式网络压下去。\n\n3 条合起来 = 5 分钟反刍打断流程，p15 给具体模板。"
    },
    {
      "id": "p10",
      "next": "p11",
      "type": "scale",
      "category": "awareness",
      "question": "**你最近 1 个月反刍频次自评（0 几乎没有，10 几乎每天发生且持续 1 小时以上）：**",
      "min": 1,
      "max": 5,
      "labels": [
        "0 到 2 分",
        "3 到 4 分",
        "5 到 6 分",
        "7 到 8 分",
        "9 到 10 分"
      ]
    },
    {
      "id": "p11",
      "next": "p12",
      "type": "single_choice",
      "category": "knowledge",
      "question": "小李心情差时习惯「躺床上一直想」，越想越糟，3 小时过去了一动没动。按今天讲的，他最该先做哪一步？",
      "options": [
        {
          "id": "opt1",
          "label": "继续躺着想清楚",
          "feedback": ""
        },
        {
          "id": "opt2",
          "label": "立刻起来做一件需要专注的事 15 到 30 分钟（出门走、做饭、给一个人打电话），先把默认模式网络压下去再说",
          "feedback": ""
        },
        {
          "id": "opt3",
          "label": "喝点酒压一压",
          "feedback": ""
        },
        {
          "id": "opt4",
          "label": "强迫自己不要想",
          "feedback": ""
        }
      ],
      "mustCorrect": true,
      "correctAnswer": "opt2"
    },
    {
      "id": "p12",
      "next": "p13",
      "type": "single_choice",
      "category": "awareness",
      "question": "下面哪一种是你**最容易陷进去**的反刍触发场景？",
      "options": [
        {
          "id": "opt1",
          "label": "跟人发生冲突后（脑子里反复演那段对话）",
          "feedback": ""
        },
        {
          "id": "opt2",
          "label": "工作 / 学业出失误后（反复想「如果当初……」)",
          "feedback": ""
        },
        {
          "id": "opt3",
          "label": "一段关系结束后（反复回想细节 + 自责）",
          "feedback": ""
        },
        {
          "id": "opt4",
          "label": "深夜躺床上（什么具体事没有，就是脑子停不下来）",
          "feedback": ""
        },
        {
          "id": "opt5",
          "label": "看到别人的某条朋友圈 / 视频后（开始比较 + 否定自己）",
          "feedback": ""
        }
      ]
    },
    {
      "id": "p13",
      "next": "p14",
      "type": "multiple_choice",
      "category": "knowledge",
      "question": "下面哪些做法**会加重**反刍，按今天讲的应该避免？（多选）",
      "options": [
        {
          "id": "opt1",
          "label": "在床上躺着「想清楚为止」",
          "feedback": ""
        },
        {
          "id": "opt2",
          "label": "强迫自己「绝对不许想这件事」（白熊效应）",
          "feedback": ""
        },
        {
          "id": "opt3",
          "label": "用刷短视频 / 喝酒来逃避（被动消遣不占工作记忆，反刍在后台继续）",
          "feedback": ""
        },
        {
          "id": "opt4",
          "label": "把「为什么我总这样」改写成「具体 X 时刻 Y 事件我做了 Z，下次做 W」",
          "feedback": ""
        }
      ],
      "mustCorrect": true,
      "correctAnswers": [
        "opt1, opt2, opt3"
      ]
    },
    {
      "id": "p14",
      "next": "p15",
      "type": "true_false",
      "category": "knowledge",
      "statement": "「反思跟反刍的关键区别有 3 条：① 反思面向未来 + 找下一步行动，反刍面向过去 + 反复回放；② 反思偏具体（X 时刻 Y 事件我做了 Z），反刍偏抽象（为什么我总这样）；③ 反思 5 到 15 分钟内能收尾，反刍 30 分钟起步且越想越乱。」这段话对吗？",
      "mustCorrect": true,
      "correctAnswer": true
    },
    {
      "id": "p15",
      "title": "🎯 今日任务：5 分钟「反刍打断」流程",
      "next": "p16",
      "buttonText": "我去做",
      "type": "content",
      "body": "今天的微行动 5 分钟，分 4 步。拿 p3 写的那件事走一遍。\n\n**Step 1（30 秒）：识别**\n问自己：「我现在脑子里反复转的这件事，是反思还是反刍？」 3 条诊断：\n- 我在面向未来还是面向过去？\n- 我在问具体问题（X 时刻 Y 事件）还是抽象问题（为什么我总这样）？\n- 我已经转了多久了？超过 15 分钟？\n\n3 条里中 2 条 → 是反刍，继续 Step 2。\n\n**Step 2（2 分钟）：抽象拉具体（Watkins 具体思维）**\n把抽象问题逐字改写成具体问题。\n\n抽象版：「为什么我总把事情搞砸？」\n改写后：「上周三晚上 8 点，我跟妈妈电话里说了 X 这句话，她沉默了 5 秒。下次我想换成 Y 这句话试试。」\n\n写在纸上 / 手机备忘录。**写下来，不要只在脑子里改**。\n\n**Step 3（30 秒）：选 1 个具体下一步**\n基于 Step 2 的改写，选 1 个本周内能做的具体动作。比如：「这周日给妈妈打一个电话，主动聊 Y 话题。」\n\n**Step 4（2 分钟）：行为激活**\n立刻起身做一件需要专注 + 占工作记忆的事 15 到 30 分钟（用计时器）。运动 / 做饭 / 打电话 / 收拾。**别刷短视频，别刷朋友圈，别喝酒**。\n\n完成。\n\n注意：\n\n- 5 分钟不要求让你「想通」，让你「跳出」\n- 一次没用就再做一次，反刍是慢性病，方法靠重复\n- Step 2 的改写是核心，没改写直接做 Step 4 容易反弹"
    },
    {
      "id": "p16",
      "next": "p17",
      "type": "single_choice",
      "category": "awareness",
      "question": "你预感 5 分钟流程里你最容易卡的是哪一步？",
      "options": [
        {
          "id": "opt1",
          "label": "Step 1 识别（分不清反思跟反刍）",
          "feedback": ""
        },
        {
          "id": "opt2",
          "label": "Step 2 抽象拉具体（写不出具体场景）",
          "feedback": ""
        },
        {
          "id": "opt3",
          "label": "Step 3 选下一步（不知道要做啥）",
          "feedback": ""
        },
        {
          "id": "opt4",
          "label": "Step 4 行为激活（起不来，就想躺着想）",
          "feedback": ""
        },
        {
          "id": "opt5",
          "label": "都容易卡",
          "feedback": ""
        }
      ]
    },
    {
      "id": "p17",
      "next": "p18",
      "type": "single_choice",
      "category": "knowledge",
      "question": "今天的 5 分钟流程最核心的作用是：",
      "options": [
        {
          "id": "opt1",
          "label": "让你想清楚那件事",
          "feedback": ""
        },
        {
          "id": "opt2",
          "label": "让你**跳出**那件事（识别 → 抽象拉具体 → 选 1 个下一步 → 起身做事），把默认模式网络压下去 + 把抽象思维拉成具体思维 + 把「想」转成「做」",
          "feedback": ""
        },
        {
          "id": "opt3",
          "label": "让你完成今天的打卡",
          "feedback": ""
        },
        {
          "id": "opt4",
          "label": "让你立刻不再难受",
          "feedback": ""
        }
      ],
      "mustCorrect": true,
      "correctAnswer": "opt2"
    },
    {
      "id": "p18",
      "next": "p19",
      "type": "single_choice",
      "category": "awareness",
      "question": "你身边那种「心情快回正 + 看上去不太纠结」的人，最大的特征是？",
      "options": [
        {
          "id": "opt1",
          "label": "他们也难受，只是难受时会去做事，不躺着想",
          "feedback": ""
        },
        {
          "id": "opt2",
          "label": "他们能把「为什么是我」很快转成「我下一步做什么」",
          "feedback": ""
        },
        {
          "id": "opt3",
          "label": "他们有意识地不让自己一个人闷着，会找人说 / 出门走",
          "feedback": ""
        },
        {
          "id": "opt4",
          "label": "我没观察过",
          "feedback": ""
        }
      ]
    },
    {
      "id": "p19",
      "title": "⚔️ 场景模拟：怎么把 5 分钟流程装进真实生活",
      "next": "p20",
      "buttonText": "开始挑战",
      "type": "content",
      "body": "下面三个场景，帮你看清「反刍打断」在实际生活里怎么做。"
    },
    {
      "id": "p20",
      "next": "p21",
      "type": "single_choice",
      "category": "knowledge",
      "question": "【场景一】小李跟同事开会被怼，回家躺床上反复演那段对话 2 小时，越想越气，连饭都不想吃。\n\n按今天讲的，他可以？",
      "options": [
        {
          "id": "opt1",
          "label": "继续躺着想到把气消完",
          "feedback": ""
        },
        {
          "id": "opt2",
          "label": "立刻起身走 5 分钟到厨房。Step 2 抽象拉具体：「会上她说的 X 那句话让我不舒服，我当时反应是 Y。下次再遇到她那种语气，我可以用 Z 这一句回。」Step 3 选下一步：「明天上班路上想 1 个具体回应模板。」Step 4 立刻去做饭 30 分钟（占工作记忆）",
          "feedback": ""
        },
        {
          "id": "opt3",
          "label": "给那个同事发一条长消息把心里话全说出来",
          "feedback": ""
        },
        {
          "id": "opt4",
          "label": "喝两杯酒压压火",
          "feedback": ""
        }
      ],
      "mustCorrect": true,
      "correctAnswer": "opt2"
    },
    {
      "id": "p21",
      "next": "p22",
      "type": "single_choice",
      "category": "knowledge",
      "question": "【场景二】小张分手 3 个月了，深夜躺床上还在反复回放最后那段对话，每次回放都是「如果当初我没说那句话……」\n\n按今天讲的，她可以？",
      "options": [
        {
          "id": "opt1",
          "label": "接受「想念是必经的」",
          "feedback": ""
        },
        {
          "id": "opt2",
          "label": "识别这是典型反刍（面向过去 + 抽象 + 持续超 30 分钟）。Step 2：「3 个月前我说了 X 这句话引发争吵。从这次我学到的具体一条是：未来吵架升级时我先停 10 分钟再说话。」Step 3 选下一步：「下次跟任何人冲突，先去阳台站 10 分钟。」Step 4 立刻起身做一件占工作记忆的事 20 分钟（出门走 / 收拾房间 / 给一个朋友打电话）",
          "feedback": ""
        },
        {
          "id": "opt3",
          "label": "把所有照片删掉",
          "feedback": ""
        },
        {
          "id": "opt4",
          "label": "找新对象",
          "feedback": ""
        }
      ],
      "mustCorrect": true,
      "correctAnswer": "opt2"
    },
    {
      "id": "p22",
      "next": "p23",
      "type": "single_choice",
      "category": "knowledge",
      "question": "【场景三】小周说：「我没什么具体烦心事，但晚上一闭眼脑子就停不下来，乱七八糟啥都想，又困又烦。」\n\n按今天讲的，他可以？",
      "options": [
        {
          "id": "opt1",
          "label": "数羊",
          "feedback": ""
        },
        {
          "id": "opt2",
          "label": "这是默认模式网络在没有任务时空转的典型状态。Step 4 优先：立刻起身做 10 分钟具体动作（写明天的 3 件事 / 收拾床头 / 喝一杯水站到窗边看 1 分钟），把默认模式网络压下去再回床上。如果躺着反复发生，固定一个「睡前 15 分钟低强度任务」（看 5 页纸质书 / 整理明天的包），从根上不让默认模式网络启动",
          "feedback": ""
        },
        {
          "id": "opt3",
          "label": "强迫自己不要想",
          "feedback": ""
        },
        {
          "id": "opt4",
          "label": "刷手机刷到困",
          "feedback": ""
        }
      ],
      "mustCorrect": true,
      "correctAnswer": "opt2"
    },
    {
      "id": "p23",
      "next": "p24",
      "type": "multiple_choice",
      "category": "knowledge",
      "question": "把今天讲的串起来，下面哪些是对的？（多选）",
      "options": [
        {
          "id": "opt1",
          "label": "反刍 = 重复 + 被动 + 无产出地回放负面事件，跟反思（面向未来 + 具体 + 短时收尾）有清晰区别",
          "feedback": ""
        },
        {
          "id": "opt2",
          "label": "Nolen-Hoeksema 30 年研究：反刍预测未来抑郁发作，抑郁加重反刍，双向放大。女性反刍倾向更高是抑郁性别差异背后的核心机制",
          "feedback": ""
        },
        {
          "id": "opt3",
          "label": "3 个有效干预：分心（占工作记忆的事） / 问题解决（抽象拉具体） / 行为激活（先动起来不等心情好）",
          "feedback": ""
        },
        {
          "id": "opt4",
          "label": "「想清楚为止不许停」是有效的反刍处理方法",
          "feedback": ""
        }
      ],
      "mustCorrect": true,
      "correctAnswers": [
        "opt1, opt2, opt3"
      ]
    },
    {
      "id": "p24",
      "next": "p25",
      "type": "text",
      "category": "awareness",
      "question": "按 p15 教的 5 分钟流程，**现在就**拿 p3 写的那件事走一遍。写下你的 Step 2 + Step 3：\n\n**「Step 2 抽象拉具体：____（X 时刻 Y 事件我做了 Z，下次我可以做 W）。Step 3 下一步具体动作：____（本周内能做的 1 件事）。」**",
      "placeholder": "例如：「Step 2：上周三晚上 8 点，跟妈电话里我说了『你别管那么多』这一句，她沉默 5 秒挂了。下次同类话题我可以换成『我自己想清楚了再告诉你』。Step 3：这周六给妈打电话，主动聊她最近在忙的事。」……",
      "required": true
    },
    {
      "id": "p25",
      "title": "练习篇 · Day 50 · 今日认知总结 · 过半节点",
      "buttonText": "完成今天",
      "type": "content",
      "body": "今天你最该带走的，就一句话：\n\n> **反刍只会越想越糟。跳出来，先别想着想通。**\n\n请记得三件事：\n\n1. **反思 ≠ 反刍**：面向未来 + 具体 + 短时收尾 才是反思\n2. **默认模式网络是元凶**：反刍时大脑被默认模式网络劫持，前额叶下调失败，停不下来是生理事实\n3. **5 分钟流程**：识别 → 抽象拉具体（Watkins） → 选 1 个下一步 → 起身做占工作记忆的事\n\n特别提示：今天是 71 天里第 50 天，过半节点。前 49 天你已经搭好了**认知 + 探索 + 部分练习**的底座。从今天开始的情绪调节系列（Day50 到 56）是练习篇里「在低谷里也能用」的工具箱。\n\n明天练习篇 Day 17：\n\n**Day51：让情绪有出口（情绪标注 + Lieberman 功能性磁共振研究）。**\n\n明天见。"
    }
  ]
}