{
  "day": 68,
  "stage": {
    "name": "内化篇",
    "stageNumber": 4,
    "color": "#7AA8D6",
    "bgColor": "#D5E5F0"
  },
  "theme": "拉个人一起练",
  "coreLine": "同伴是坚持的最大放大器",
  "totalPages": 25,
  "pages": [
    {
      "id": "p1",
      "next": "p2",
      "buttonText": "开始今天",
      "type": "content",
      "body": "欢迎进入内化篇第 7 天。\n\n你已经走过 67 天。手里大概攒了 5 个能用的工具：感恩、品味、优势、回应好消息、写日记，可能再加一两个偏好工具。\n\n但有一件事得跟你坦白讲。\n\n**到第 3 周左右，绝大多数人会掉线。**\n\n工具其实没问题。问题在于「一个人练」这件事，本身就反人类。\n\nLyubomirsky 在书里反复讲一句话：\n\n> 幸福干预最难的不是学，难在坚持。\n\n她追踪过很多受试者，结论很直白：\n\n- 4 周内还在练的人，70% 左右\n- 8 周降到 50%\n- 12 周以后，独自练的人剩不到 30%\n\n那被砍掉的 40% 到 70% 里，工具知识他们都懂。他们就是「自己提不起劲再做一次」。\n\n破局点不在工具。在你身边有没有一个**人**。\n\n今天讲的就是：怎么用「拉一个人」把坚持率拉回来。"
    },
    {
      "id": "p2",
      "next": "p3",
      "type": "single_choice",
      "category": "awareness",
      "question": "你过去 67 天里有没有跟某个人「**聊过**」幸福计划在做什么？（不限深度，哪怕一句话）",
      "options": [
        {
          "id": "opt1",
          "label": "没有，从头到尾自己默默做",
          "feedback": "典型状态。今天的内容直接针对你。"
        },
        {
          "id": "opt2",
          "label": "提过一句但对方没接，就没继续",
          "feedback": "常见。今天会教你『怎么开口对方才会接』。"
        },
        {
          "id": "opt3",
          "label": "跟 1-2 个人简单聊过",
          "feedback": "有起点。今天会告诉你怎么把『聊过』升级成『一起练』。"
        },
        {
          "id": "opt4",
          "label": "有 1 个人比较了解我在练什么",
          "feedback": "这就是高坚持的起点。今天教你怎么把这个人变成正式同伴。"
        },
        {
          "id": "opt5",
          "label": "有几个人甚至跟我一起在练",
          "feedback": "极佳。你已经无意中走在了正确路径上。今天给你结构化框架。"
        }
      ]
    },
    {
      "id": "p3",
      "next": "p4",
      "type": "text",
      "category": "awareness",
      "question": "凭直觉写下来：\n\n**「过去 67 天里我最容易掉线 / 不想做的那一周或那几天，背后的真实原因是 ____。」**",
      "placeholder": "例如：「第 3 周那几天工作忙，没人催就放下了」「上次回老家一周，环境一变就停了」「有一次心情低没人陪我聊，自己就摆烂了」「想不起来」……",
      "required": true
    },
    {
      "id": "p4",
      "title": "📖 今日完整阅读",
      "next": "p5",
      "buttonText": "读完了，开始做题",
      "type": "content"
    },
    {
      "id": "p5",
      "next": "p6",
      "type": "single_choice",
      "category": "knowledge",
      "question": "Christakis 和 Fowler 2008 年那本书，基于一项 32 年的纵向追踪数据，得出的结论是什么？",
      "options": [
        {
          "id": "opt1",
          "label": "幸福只能靠自己",
          "feedback": ""
        },
        {
          "id": "opt2",
          "label": "幸福、肥胖、抽烟、抑郁都会沿着关系网传染。一个朋友变幸福，你变幸福的概率提升 15%",
          "feedback": ""
        },
        {
          "id": "opt3",
          "label": "朋友多的人一定幸福",
          "feedback": ""
        },
        {
          "id": "opt4",
          "label": "社交跟幸福无关",
          "feedback": ""
        }
      ],
      "mustCorrect": true,
      "correctAnswer": "opt2"
    },
    {
      "id": "p6",
      "next": "p7",
      "type": "multiple_choice",
      "category": "knowledge",
      "question": "下面哪些属于 Christakis 和 Fowler 提出的「三度影响力」？（多选）",
      "options": [
        {
          "id": "opt1",
          "label": "你的朋友变幸福，你的幸福概率提升约 15%（一度）",
          "feedback": ""
        },
        {
          "id": "opt2",
          "label": "朋友的朋友变幸福，你的幸福概率提升约 10%（二度）",
          "feedback": ""
        },
        {
          "id": "opt3",
          "label": "朋友的朋友的朋友变幸福，你的幸福概率提升约 6%（三度）",
          "feedback": ""
        },
        {
          "id": "opt4",
          "label": "影响范围无限，传到天涯海角都有效",
          "feedback": ""
        }
      ],
      "mustCorrect": true,
      "correctAnswers": [
        "opt1, opt2, opt3"
      ]
    },
    {
      "id": "p7",
      "next": "p8",
      "type": "true_false",
      "category": "knowledge",
      "statement": "「Wing 和 Jeffery 1999 那项减肥研究里，4 人小组完成率 95%，独自参加只有 76%。差距来自『团里有人盯着你，你不想让团队失望，互相打气』，跟工具本身没关系。也就是说同样的工具，有没有人陪着练，完成率天差地别。」这句话对吗？",
      "mustCorrect": true,
      "correctAnswer": true
    },
    {
      "id": "p8",
      "next": "p9",
      "type": "single_choice",
      "category": "knowledge",
      "question": "Bandura 社会学习理论的核心机制是什么？",
      "options": [
        {
          "id": "opt1",
          "label": "人主要靠书本学习",
          "feedback": ""
        },
        {
          "id": "opt2",
          "label": "人主要靠观察别人的行为学会新行为。再加上看到别人因为这个行为被奖励，把行为维持下来",
          "feedback": ""
        },
        {
          "id": "opt3",
          "label": "人只能靠自己摸索",
          "feedback": ""
        },
        {
          "id": "opt4",
          "label": "学习跟环境无关",
          "feedback": ""
        }
      ],
      "mustCorrect": true,
      "correctAnswer": "opt2"
    },
    {
      "id": "p9",
      "title": "💡 它和你有什么关系",
      "next": "p10",
      "buttonText": "明白了",
      "type": "content",
      "body": "「我自己默默练就行」这句话听上去成熟，实际上是高坚持率的最大杀手。\n\n3 个机制叠在一起。\n\n**机制 1：动力衰减**\n人对自己许下的承诺，会随着时间打折。研究里叫承诺消退。第 1 周热情 100%，第 3 周 30%。这是人之常情。但你对一个具体的人许下的承诺，衰减慢得多，因为「让人失望」的成本明显高于「让自己失望」。\n\n**机制 2：观察学习中断**\n你独自练，看不到「这个工具在别人身上长什么样」。一旦遇到卡点，没有参照物，自己琢磨，容易得出错误结论（「这个对我没用」）。身边有 1 个人在练，你能看到他的具体做法和具体反馈，卡点 1 分钟就过了。\n\n**机制 3：社交奖励缺失**\n做一件事的爽，70% 来自「跟人分享 / 被看见」。独自练，做了等于没做，大脑给不出奖励，第 2 次更不想做。有人接住你的分享，大脑得到奖励，下一次自动想做。这是 Day24 回应好消息那一招的反向应用。\n\n3 个机制叠起来，独自练的人在第 3 周左右掉线，跟意志力没关系，跟工具好不好用也没关系。\n\n破局非常便宜：\n\n**找 1 个人，告诉他你在做什么，让他知道你这一周打算做什么。**\n\n不需要他跟你一起做（虽然一起做更好）。只需要他**知道**。\n\nGoldstein 2008 年那个酒店毛巾实验更狠。他在酒店挂了两种标语。\n\nA 版：「为了环保，请重复使用毛巾。」\nB 版：「**这间房 75% 的客人都重复使用了毛巾**。」\n\nB 版比 A 版多 26% 的人照做。\n\n什么意思？人对「跟我类似的人都在做」这个信息极度敏感。告诉你身边的人「我在做幸福计划」，他不需要做什么，他存在本身就会反过来影响你。"
    },
    {
      "id": "p10",
      "next": "p11",
      "type": "scale",
      "category": "awareness",
      "question": "**你目前身边「知道你在练这件事，又愿意接住你聊它」的人数自评（0 完全没有，10 有 3 个以上）：**",
      "min": 1,
      "max": 5,
      "labels": [
        "0–2 分",
        "3–4 分",
        "5–6 分",
        "7–8 分",
        "9–10 分"
      ]
    },
    {
      "id": "p11",
      "next": "p12",
      "type": "single_choice",
      "category": "knowledge",
      "question": "小李说「我朋友都不在练这种东西，没人陪我」。按今天讲的，他最快的破局动作是？",
      "options": [
        {
          "id": "opt1",
          "label": "等到身边有人主动开始练才说",
          "feedback": ""
        },
        {
          "id": "opt2",
          "label": "主动开口找 1 个最容易接住你的朋友，说「我在做 71 天幸福计划，想找个人每周互相聊 10 分钟，你愿意吗？」**他不必跟你一起做**，只需要听",
          "feedback": ""
        },
        {
          "id": "opt3",
          "label": "戒掉所有朋友",
          "feedback": ""
        },
        {
          "id": "opt4",
          "label": "放弃幸福计划",
          "feedback": ""
        }
      ],
      "mustCorrect": true,
      "correctAnswer": "opt2"
    },
    {
      "id": "p12",
      "next": "p13",
      "type": "single_choice",
      "category": "awareness",
      "question": "下面 4 类同伴，今天你**最容易**先拿到的是哪一类？",
      "options": [
        {
          "id": "opt1",
          "label": "互相打卡的伙伴：每周固定时间问对方一句「这周做到了吗」",
          "feedback": ""
        },
        {
          "id": "opt2",
          "label": "共同练习者：跟你一起做某个具体动作（比如一起每天写「今天三件好事」）",
          "feedback": ""
        },
        {
          "id": "opt3",
          "label": "高榜样：身边已经在「过得有意思 / 心态稳」的人，定期跟他喝个咖啡偷学",
          "feedback": ""
        },
        {
          "id": "opt4",
          "label": "同向社群：豆瓣小组 / 微信群 / 读书会，被「一群人在练」氛围裹挟",
          "feedback": ""
        }
      ]
    },
    {
      "id": "p13",
      "next": "p14",
      "type": "multiple_choice",
      "category": "knowledge",
      "question": "下面哪些是「找同伴」的 4 类正确分类？（多选）",
      "options": [
        {
          "id": "opt1",
          "label": "互相打卡的伙伴",
          "feedback": ""
        },
        {
          "id": "opt2",
          "label": "共同练习者（一起做某个动作）",
          "feedback": ""
        },
        {
          "id": "opt3",
          "label": "高榜样（学习对象，定期接触）",
          "feedback": ""
        },
        {
          "id": "opt4",
          "label": "同向社群（豆瓣小组 / 微信群 / 读书会）",
          "feedback": ""
        }
      ],
      "mustCorrect": true,
      "correctAnswers": [
        "opt1, opt2, opt3, opt4"
      ]
    },
    {
      "id": "p14",
      "next": "p15",
      "type": "true_false",
      "category": "knowledge",
      "statement": "「『我自己练就行，不用麻烦别人』这句话听起来很懂事，背后其实是怕被拒绝。研究反复证明，单兵作战在第 3 周左右掉线率超过 50%，有社交支撑能把这个数字砍掉一半。所以『拉个人一起练』跟『独立人格』不冲突，它是一个**技术性增益动作**。」这句话对吗？",
      "mustCorrect": true,
      "correctAnswer": true
    },
    {
      "id": "p15",
      "title": "🎯 今日任务：5 分钟「3 句话邀请」",
      "next": "p16",
      "buttonText": "我去发",
      "type": "content",
      "body": "今天的微行动 5 分钟。\n\n**第 1 步**：从你的微信通讯录里挑 **1 个最容易开口**的人。判别标准：\n\n- 你跟他聊近况不会尴尬\n- 他给过你正面回应\n- 你预感他听到「幸福计划」不会笑你\n\n**第 2 步**：用下面 3 句话模板发给他（可改成你的语气）：\n\n> **「Hey，我最近在做一个 71 天的幸福计划（耶鲁那门《幸福的科学》的衍生），已经做到 Day68 了。**\n>\n> **想找个人每周互相聊 10 分钟，就聊这周做了什么、感觉怎样、有什么卡点。**\n>\n> **不用你跟我一起做，就是想有个人听一下。你愿意吗？」**\n\n**第 3 步**：发出去。**今天就发**。\n\n**注意**：\n\n- 如果他没回 / 拒绝 / 反应冷淡，**不解释不追问**，换下一个人。被拒绝是正常的，不代表关系出了问题\n- 如果他答应了，下一步是约**第一次 10 分钟通话或见面**（这周内）\n- 不要发给 3 个以上的人，找到 1 个就停。质量大于数量"
    },
    {
      "id": "p16",
      "next": "p17",
      "type": "single_choice",
      "category": "awareness",
      "question": "你预感开口邀请最容易卡的环节是哪一个？",
      "options": [
        {
          "id": "opt1",
          "label": "挑人（不知道挑谁）",
          "feedback": ""
        },
        {
          "id": "opt2",
          "label": "措辞（怕显得做作 / 矫情）",
          "feedback": ""
        },
        {
          "id": "opt3",
          "label": "发出去那一刻（怕被拒 / 怕没回应）",
          "feedback": ""
        },
        {
          "id": "opt4",
          "label": "对方答应之后的第一次聊（不知道聊什么）",
          "feedback": ""
        },
        {
          "id": "opt5",
          "label": "都容易卡",
          "feedback": ""
        }
      ]
    },
    {
      "id": "p17",
      "next": "p18",
      "type": "single_choice",
      "category": "knowledge",
      "question": "今天的微行动最核心的作用是：",
      "options": [
        {
          "id": "opt1",
          "label": "让你多 1 个朋友",
          "feedback": ""
        },
        {
          "id": "opt2",
          "label": "用 1 次具体的开口，把「同伴是放大器」从一句道理变成你身上一个真实的关系节点。开口成本 5 分钟，回报是剩下 3 天加上后续几个月的坚持率明显往上走",
          "feedback": ""
        },
        {
          "id": "opt3",
          "label": "完成今天的打卡",
          "feedback": ""
        },
        {
          "id": "opt4",
          "label": "显得你很努力",
          "feedback": ""
        }
      ],
      "mustCorrect": true,
      "correctAnswer": "opt2"
    },
    {
      "id": "p18",
      "next": "p19",
      "type": "single_choice",
      "category": "awareness",
      "question": "你身边那种「自己能稳定坚持一件事好几年」的人，他们最大的共同特征是？",
      "options": [
        {
          "id": "opt1",
          "label": "他们都有一个固定的人在某种意义上「陪着」（伴侣 / 老友 / 教练 / 社群）",
          "feedback": ""
        },
        {
          "id": "opt2",
          "label": "他们意志力比别人强",
          "feedback": ""
        },
        {
          "id": "opt3",
          "label": "他们没什么社交，所以能专注",
          "feedback": ""
        },
        {
          "id": "opt4",
          "label": "我没观察过",
          "feedback": ""
        }
      ]
    },
    {
      "id": "p19",
      "title": "⚔️ 场景模拟：怎么把「同伴」装进现实",
      "next": "p20",
      "buttonText": "开始挑战",
      "type": "content",
      "body": "下面三个场景，帮你看清「找同伴」在真实关系里怎么落地。"
    },
    {
      "id": "p20",
      "next": "p21",
      "type": "single_choice",
      "category": "knowledge",
      "question": "【场景一】小李身边大多数朋友都「不聊这种内省的事」，他觉得说出来会被笑。\n\n按今天讲的，他可以？",
      "options": [
        {
          "id": "opt1",
          "label": "等到身边的人都改变了再说",
          "feedback": ""
        },
        {
          "id": "opt2",
          "label": "跳过身边那些大概率会笑的人，先找 1 个最不会笑你的人（哪怕只是大学同学一年没怎么联系）。同时加 1 个豆瓣小组 / 读书群（同向社群）做底层支撑。**身边 1 个人加上 1 个群**已经够了",
          "feedback": ""
        },
        {
          "id": "opt3",
          "label": "跟所有人摊牌",
          "feedback": ""
        },
        {
          "id": "opt4",
          "label": "放弃幸福计划",
          "feedback": ""
        }
      ],
      "mustCorrect": true,
      "correctAnswer": "opt2"
    },
    {
      "id": "p21",
      "next": "p22",
      "type": "single_choice",
      "category": "knowledge",
      "question": "【场景二】小张找了朋友互相打卡，第 2 周朋友就不回消息了。她觉得「人家也没空，算了」。\n\n按今天讲的，她可以？",
      "options": [
        {
          "id": "opt1",
          "label": "算了",
          "feedback": ""
        },
        {
          "id": "opt2",
          "label": "先**不追问朋友为什么不回**（朋友可能只是忙）。再开口找第 2 个候选人。同时把「互相打卡」改成更轻的版本：每周日晚上发 1 条 30 秒语音「这周我做了 X，感觉 Y」，**对方不必回**。降低对方的心理负担，存活率会显著上升",
          "feedback": ""
        },
        {
          "id": "opt3",
          "label": "跟朋友绝交",
          "feedback": ""
        },
        {
          "id": "opt4",
          "label": "强迫朋友回",
          "feedback": ""
        }
      ],
      "mustCorrect": true,
      "correctAnswer": "opt2"
    },
    {
      "id": "p22",
      "next": "p23",
      "type": "single_choice",
      "category": "knowledge",
      "question": "【场景三】小周身边「没有任何人在做这种东西」，他在二线城市，社交圈固定。\n\n按今天讲的，他可以？",
      "options": [
        {
          "id": "opt1",
          "label": "自己默默扛",
          "feedback": ""
        },
        {
          "id": "opt2",
          "label": "优先走「同向社群」这条线：豆瓣「幸福研究」「积极心理学」相关小组、微信「自我成长」类社群、读书会的线上版本。**陌生但同向的人**比身边但不同向的人更能给你坚持感。同时给伴侣 / 父母 / 1 个老友报备一句「我最近在做 X」，他不必懂",
          "feedback": ""
        },
        {
          "id": "opt3",
          "label": "等到自己幸福了再开口",
          "feedback": ""
        },
        {
          "id": "opt4",
          "label": "搬到一线城市",
          "feedback": ""
        }
      ],
      "mustCorrect": true,
      "correctAnswer": "opt2"
    },
    {
      "id": "p23",
      "next": "p24",
      "type": "multiple_choice",
      "category": "knowledge",
      "question": "把今天讲的串起来，下面哪些是对的？（多选）",
      "options": [
        {
          "id": "opt1",
          "label": "Christakis 和 Fowler 32 年的纵向数据：幸福沿网络传染，三度影响力（朋友 15% / 朋友的朋友 10% / 第三度约 6%）",
          "feedback": ""
        },
        {
          "id": "opt2",
          "label": "Wing 和 Jeffery 1999：4 人小组减肥完成率 95%，独自参加 76%，差距来自社交支撑",
          "feedback": ""
        },
        {
          "id": "opt3",
          "label": "Goldstein 2008 酒店毛巾实验：「这间房 75% 客人都重复用毛巾」比环保口号多 26% 的人照做，说明人对「跟我类似的人都在做」高度敏感",
          "feedback": ""
        },
        {
          "id": "opt4",
          "label": "单兵作战是高坚持率的最优解",
          "feedback": ""
        }
      ],
      "mustCorrect": true,
      "correctAnswers": [
        "opt1, opt2, opt3"
      ]
    },
    {
      "id": "p24",
      "next": "p25",
      "type": "text",
      "category": "awareness",
      "question": "按 p15 教的方法，写下你的开口计划：\n\n**「今天我打算开口的那 1 个人是 ____（关系 + 名字首字母）。我打算发的版本是 ____。如果对方答应了，我们的第一次 10 分钟聊聊安排在 ____。」**",
      "placeholder": "例如：「1. 大学室友 W；2. Hey W，我最近在做一个 71 天的幸福计划，已经到 Day68 了，想找个人每周互相聊 10 分钟，不用你跟我一起做，就想有个人听一下，你愿意吗？；3. 这周日晚 9 点视频。」……",
      "required": true
    },
    {
      "id": "p25",
      "title": "内化篇 · Day68 · 今日认知总结",
      "buttonText": "完成今天",
      "type": "content",
      "body": "今天你最该带走的，就一句话：\n\n> **同伴是坚持的最大放大器。**\n\n请记得三件事：\n\n1. **Christakis 和 Fowler 三度影响力**：幸福沿社交网络传染，朋友 15% / 朋友的朋友 10% / 第三度约 6%\n2. **找伙伴 4 类**：互相打卡的伙伴 / 共同练习者 / 高榜样 / 同向社群。至少先拿 1 类\n3. **3 句话开口模板**：说清楚「我在做什么 + 我想要什么 + 你不必跟我一起做」，今天就发\n\n明天内化篇 Day 8：\n\n**Day69：让幸福计划长在生活里（怎么把今天学的工具塞进未来 1 年的节奏，再加一套防回潮 SOP）。**\n\n明天见。"
    }
  ]
}